mkdocs_s7_tt/__init__.py
mkdocs_s7_tt/main.py
mkdocs_s7_tt/modules/__init__.py
mkdocs_s7_tt/modules/data_cleaning.py
mkdocs_s7_tt/modules/doc_generation.py
mkdocs_s7_tt/modules/usable.py
mkdocs_s7_tt-1.7.0.dist-info/METADATA
mkdocs_s7_tt-1.7.0.dist-info/WHEEL
mkdocs_s7_tt-1.7.0.dist-info/entry_points.txt
mkdocs_s7_tt-1.7.0.dist-info/top_level.txt
mkdocs_s7_tt-1.7.0.dist-info/RECORD
