Metadata-Version: 2.1
Name: mkdocs-s7-tt
Version: 1.7.0
Summary: Um pacote python de geração de documentos automáticos
Author: Bruno Ribeiro, Bruno Martins, Diógenes Dantas, Igor Penha, Lucas Gobbi e Rafael Nobre
Author-email: rafaelmedeirosnobre2001@gmail.com
License: MIT
Keywords: mkdocs_s7_tt
Classifier: Programming Language :: Python :: 3
Classifier: License :: OSI Approved :: MIT License
Classifier: Operating System :: OS Independent
Requires-Dist: mdpdf (==0.0.18)
Requires-Dist: pandas (==1.5.2)
